pg_stage/__init__.py
pg_stage/mimesis_interface.py
pg_stage/mutator.py
pg_stage/obfuscator.py
pg_stage/typing.py
pg_stage-1.0.0.dist-info/METADATA
pg_stage-1.0.0.dist-info/WHEEL
pg_stage-1.0.0.dist-info/licenses/LICENSE.txt
pg_stage-1.0.0.dist-info/RECORD
