Metadata-Version: 2.3
Name: pg_stage
Version: 1.0.0
Summary: Anonymization of data in pg_dump
Project-URL: Homepage, https://github.com/froOzzy/pg_stage
Author-email: froOzzy <ieme5gll6u78@mail.ru>
License-File: LICENSE.txt
Classifier: License :: OSI Approved :: MIT License
Classifier: Operating System :: OS Independent
Classifier: Programming Language :: Python :: 3
Requires-Python: >=3.9
Requires-Dist: faker>=16.6.0
Requires-Dist: typing-extensions>=4.5.0
